Metadata-Version: 2.1
Name: kfactionlogger2
Version: 0.0.2
Summary: L'Anti-afk principal Kfaction by prouteur
Home-page: UNKNOWN
Author: Prouteur
Author-email: kazendonovan@gmail.com
License: MIT
Keywords: meth
Platform: UNKNOWN
Classifier: Development Status :: 5 - Production/Stable
Classifier: Intended Audience :: Education
Classifier: Operating System :: Microsoft :: Windows :: Windows 10
Classifier: License :: OSI Approved :: MIT License
Classifier: Programming Language :: Python :: 3
License-File: LICENCE.txt
